ambientweather2sqlite/__init__.py
ambientweather2sqlite/__main__.py
ambientweather2sqlite/awparser.py
ambientweather2sqlite/configuration.py
ambientweather2sqlite/daemon.py
ambientweather2sqlite/database.py
ambientweather2sqlite/exceptions.py
ambientweather2sqlite/metadata.py
ambientweather2sqlite/mureq.py
ambientweather2sqlite/server.py
ambientweather2sqlite/units_mapping.py
ambientweather2sqlite-0.6.1.dist-info/licenses/LICENSE.md
ambientweather2sqlite-0.6.1.dist-info/METADATA
ambientweather2sqlite-0.6.1.dist-info/WHEEL
ambientweather2sqlite-0.6.1.dist-info/entry_points.txt
ambientweather2sqlite-0.6.1.dist-info/top_level.txt
ambientweather2sqlite-0.6.1.dist-info/RECORD
