Metadata-Version: 2.4
Name: ambientweather2sqlite
Version: 0.6.1
Summary: A project to record weather observations from an AmbientWeather station over the local network - no API needed!
Author-email: Harold Martin <Harold.Martin@gmail.com>
License-Expression: GPL-3.0-or-later
Keywords: ambientweather,ambient,sqlite,tweather
Classifier: Development Status :: 4 - Beta
Classifier: Environment :: Console
Classifier: Framework :: Datasette
Classifier: Intended Audience :: End Users/Desktop
Classifier: Intended Audience :: Science/Research
Classifier: Programming Language :: Python :: 3.11
Classifier: Programming Language :: Python :: 3.12
Classifier: Programming Language :: Python :: 3.13
Classifier: Programming Language :: Python :: 3.14
Classifier: Typing :: Typed
Requires-Python: >=3.11
License-File: LICENSE.md
Dynamic: license-file
